pyqiwip2p/AioQiwip2p.py
pyqiwip2p/Qiwip2p.py
pyqiwip2p/__init__.py
pyqiwip2p/notify/__init__.py
pyqiwip2p/notify/async_client.py
pyqiwip2p/p2p_types/__init__.py
pyqiwip2p/p2p_types/custom_fields.py
pyqiwip2p/p2p_types/customer.py
pyqiwip2p/p2p_types/errors.py
pyqiwip2p/p2p_types/qiwi_datetime.py
pyqiwip2p/p2p_types/responses.py
pyQiwiP2P-2.0.7.dist-info/LICENSE
pyQiwiP2P-2.0.7.dist-info/METADATA
pyQiwiP2P-2.0.7.dist-info/WHEEL
pyQiwiP2P-2.0.7.dist-info/top_level.txt
pyQiwiP2P-2.0.7.dist-info/RECORD
