Metadata-Version: 2.1
Name: pyQiwiP2P
Version: 2.0.7
Summary: pyQiwiP2P
Home-page: https://github.com/WhiteApfel/pyQiwiP2P
Author: WhiteApfel
Author-email: white@pfel.ru
License: Mozilla Public License 2.0
Project-URL: Документальное чтиво, https://pyqiwip2p.readthedocs.io/ru/latest/
Project-URL: Донатик, https://pfel.cc/donate
Project-URL: Исходнички, https://github.com/WhiteApfel/pyQiwiP2P
Project-URL: Тележка для вопросов, https://t.me/apfel
Keywords: qiwip2p api qiwi p2p payments bill tools sdk wrapper
License-File: LICENSE
Requires-Dist: setuptools (>=63.1.0)
Requires-Dist: phonenumbers (>=8.12.15)
Requires-Dist: email-validator (>=1.2.1)
Requires-Dist: typing (>=3.7.4.3)
Requires-Dist: Hypercorn (>=0.11.2)
Requires-Dist: starlette (>=0.19.0)
Requires-Dist: httpx (>=0.23.0)
Requires-Dist: pydantic (>=1.9.1)
Requires-Dist: validators (>=0.20.0)
Requires-Dist: ipaddress (~=1.0.23)
Requires-Dist: loguru (>=0.6.0)
Requires-Dist: python-dotenv (>=0.20.0)
Requires-Dist: pytest (>=7.1.2)
Requires-Dist: CherryPy (>=18.7.0)
Requires-Dist: response-report (~=1.1.0)
